[
    
    {"k":"1","q":"مع اي حرف نظهر النون",
    "ch1":"ء",
    "ch2":"م",
    "r":"ء"},
    
    
    {"k":"1","q":"مع اي حرف نظهر النون",
    "ch1":"ت",
    "ch2":"ح",
    "r":"ح"},
    
    {"k":"1","q":"مع اي حرف نظهر النون",
    "ch1":"د",
    "ch2":"غ",
    "r":"غ"},
    
    {"k":"1","q":"مع اي حرف نظهر النون",
    "ch1":"ه",
    "ch2":"ك",
    "r":"ه"},
    
    
    {"k":"1","q":"مع اي حرف نظهر النون",
    "ch1":"خ",
    "ch2":"ش",
    "r":"خ"},
    
    
    
    {"k":"1","q":"مع اي حرف نظهر النون",
    "ch1":"ع",
    "ch2":"ش",
    "r":"ع"},
    
    
    {"k":"1","q":"مع اي حرف ندغم النون",
    "ch1":"خ",
    "ch2":"ل",
    "r":"ل"},
    
    
    {"k":"1","q":"مع اي حرف ندغم النون",
    "ch1":"ر",
    "ch2":"ظ",
    "r":"ر"},
    
    
    {"k":"1","q":"مع اي حرف ندغم النون",
    "ch1":"ي",
    "ch2":"ك",
    "r":"ي"},
    
    
    {"k":"1","q":"مع اي حرف ندغم النون",
    "ch1":"م",
    "ch2":"ت",
    "r":"م"},
    
    
    {"k":"1","q":"مع اي حرف ندغم النون",
    "ch1":"خ",
    "ch2":"و",
    "r":"و"},
    
    
    {"k":"1","q":"مع اي حرف ندغم النون",
    "ch1":"ض",
    "ch2":"ن",
    "r":"ن"},
    
    
    {"k":"1","q":"مع اي حرف ندغم النون",
    "ch1":"خ",
    "ch2":"ل",
    "r":"ل"}
    ,{"k":"0","q":"من سورة النبأ اكمل:عم يتساءلون",
        "ch1":"عن النبأ العظيم",
        "ch2":"كلا سيعلمون",
        "r":"عن النبأ العظيم"}
        ,{"k":"0","q":"من سورة النبأ اكمل:عن النبأ العظيم",
            "ch1":"الذي هم فيه مختلفون",
            "ch2":"كلا سيعلمون",
            "r":"كلا سيعلمون"}

            ,{"k":"0","q":"من سورة النبأ اكمل:كلا سيعلمون",
                "ch1":"الذي هم فيه مختلفون",
                "ch2":"ثم كلا سيعلمون ",
                "r":"ثم كلا سيعلمون"}
                ,{"k":"0","q":" من سورة النبأ اكمل:ثم كلا سيعلمون",
                    "ch1":"الم نجعل الارض مهادا",
                    "ch2":"ثم كلا سيعلمون ",
                    "r":"الم نجعل الارض مهادا"}
                    ,{"k":"0","q":" من سورة النبأ اكمل:الم نجعل الارض مهادا",
                        "ch1":"وخلقناكم ازواجا",
                        "ch2":"والجبال اوتادا ",
                        "r":"والجبال اوتادا "}
                        ,{"k":"0","q":" من سورة النبأ اكمل:وجعلنا الليل لباسا",
                            "ch1":"وجعلناالنهار معاشا",
                            "ch2":"والجبال اوتادا ",
                            "r":"وجعلناالنهار معاشا "}
            
                            ,{"k":"0","q":" من سورة النبأ اكمل:وجعلناالنهار معاشا",
                                "ch1":"وجعلنا سراجا وهاجا",
                                "ch2":"و بنينا فوقكم سبعا شدادا ",
                                "r":"و بنينا فوقكم سبعا شدادا "}



                                ,{"k":"0","q":" من سورة النبأ اكمل:وجعلنا سراجا وهاجا",
                                    "ch1":"وأنزلنا من المعصرات مآء ثجاجا",
                                    "ch2":"لنخرج به حبا ونباتا",
                                    "r":"وأنزلنا من المعصرات مآء ثجاجا"}


                                    ,{"k":"0","q":" من سورة النبأ اكمل:وجنت الفافا",
                                        "ch1":"وفتحت السماء فكانت ابوابا",
                                        "ch2":"ان يوم الفصل كان ميقاتا",
                                        "r":"ان يوم الفصل كان ميقاتا"}
    
                                        ,{"k":"0","q":" من سورة النبأ اكمل:للطغين مئابا",
                                            "ch1":"لا يذوقون فيها بردا و لا شرابا",
                                            "ch2":"لبثين فيهآ احقابا",
                                            "r":"لبثين فيهآ احقابا"}

                                            ,{"k":"0","q":" من سورة النبأ اكمل:ان للمتقين مفازا",
                                                "ch1":"حدآئق و اعنابا",
                                                "ch2":"وكواعب اترابا",
                                                "r":"حدآئق و اعنابا"}
    
]
    
    